examples/basic_charts.py
examples/generate_demo.py
tests/__init__.py
tests/conftest.py
tests/test_backend_selection.py
tests/test_chart.py
tests/test_drawings.py
tests/test_schema.py
tests/test_transforms.py
wrchart/__init__.py
wrchart/financial.py
wrchart/core/__init__.py
wrchart/core/chart.py
wrchart/core/schema.py
wrchart/core/series.py
wrchart/core/themes.py
wrchart/core/webgl_chart.py
wrchart/core/backends/__init__.py
wrchart/core/backends/base.py
wrchart/core/backends/canvas.py
wrchart/core/backends/lightweight.py
wrchart/core/backends/multipanel.py
wrchart/core/backends/webgl.py
wrchart/drawing/__init__.py
wrchart/drawing/tools.py
wrchart/forecast/__init__.py
wrchart/forecast/chart.py
wrchart/forecast/colorscales.py
wrchart/forecast/utils.py
wrchart/indicators/__init__.py
wrchart/indicators/oscillators.py
wrchart/indicators/overlays.py
wrchart/live/__init__.py
wrchart/live/chart.py
wrchart/live/dashboard.py
wrchart/live/server.py
wrchart/live/table.py
wrchart/multipanel/__init__.py
wrchart/multipanel/chart.py
wrchart/multipanel/panels.py
wrchart/transforms/__init__.py
wrchart/transforms/decimation.py
wrchart/transforms/heikin_ashi.py
wrchart/transforms/kagi.py
wrchart/transforms/line_break.py
wrchart/transforms/pnf.py
wrchart/transforms/range_bar.py
wrchart/transforms/renko.py
wrchart/widget/__init__.py
wrchart-0.2.0.dist-info/METADATA
wrchart-0.2.0.dist-info/WHEEL
wrchart-0.2.0.dist-info/top_level.txt
wrchart-0.2.0.dist-info/RECORD
