Metadata-Version: 2.4
Name: wrchart
Version: 0.2.0
Summary: Interactive financial charting library with Polars support and TradingView-style aesthetics
Home-page: https://github.com/wayy-research/wrchart
Author: Wayy Research
Author-email: Wayy Research <contact@wayy.research>
License-Expression: MIT
Project-URL: Homepage, https://github.com/wayy-research/wrchart
Project-URL: Documentation, https://wrchart.readthedocs.io/
Project-URL: Repository, https://github.com/wayy-research/wrchart
Project-URL: Bug Tracker, https://github.com/wayy-research/wrchart/issues
Keywords: charting,trading,finance,visualization,candlestick,renko,kagi,polars,jupyter,interactive
Classifier: Development Status :: 3 - Alpha
Classifier: Intended Audience :: Financial and Insurance Industry
Classifier: Intended Audience :: Developers
Classifier: Intended Audience :: Science/Research
Classifier: Operating System :: OS Independent
Classifier: Programming Language :: Python :: 3
Classifier: Programming Language :: Python :: 3.9
Classifier: Programming Language :: Python :: 3.10
Classifier: Programming Language :: Python :: 3.11
Classifier: Programming Language :: Python :: 3.12
Classifier: Topic :: Office/Business :: Financial :: Investment
Classifier: Topic :: Scientific/Engineering :: Visualization
Classifier: Framework :: Jupyter
Requires-Python: >=3.9
Requires-Dist: polars>=0.20.0
Requires-Dist: numpy>=1.21.0
Provides-Extra: jupyter
Requires-Dist: ipywidgets>=8.0.0; extra == "jupyter"
Requires-Dist: jupyterlab>=4.0.0; extra == "jupyter"
Provides-Extra: dev
Requires-Dist: pytest>=7.0.0; extra == "dev"
Requires-Dist: pytest-cov>=4.0.0; extra == "dev"
Requires-Dist: black>=23.0.0; extra == "dev"
Requires-Dist: ruff>=0.1.0; extra == "dev"
Requires-Dist: mypy>=1.0.0; extra == "dev"
Provides-Extra: all
Requires-Dist: ipywidgets>=8.0.0; extra == "all"
Requires-Dist: jupyterlab>=4.0.0; extra == "all"
Dynamic: author
Dynamic: home-page
Dynamic: requires-python
